elabtui/__init__.py
elabtui/__main__.py
elabtui/elabtui.py
elabtui-0.2.2.dist-info/DESCRIPTION.rst
elabtui-0.2.2.dist-info/METADATA
elabtui-0.2.2.dist-info/RECORD
elabtui-0.2.2.dist-info/WHEEL
elabtui-0.2.2.dist-info/entry_points.txt
elabtui-0.2.2.dist-info/metadata.json
elabtui-0.2.2.dist-info/top_level.txt
