Metadata-Version: 2.0
Name: elabtui
Version: 0.2.2
Summary: elabftw text user interface to manage experiments
Home-page: https://github.com/elabftw/elabtui
Author: Nicolas CARPi
Author-email: nicolas.carpi@curie.fr
License: GPL v3
Platform: UNKNOWN
Requires-Dist: asciimatics
Requires-Dist: elabapy
Requires-Dist: pyyaml
